{"id":"4iof5rfj4t46eutdqzrax6k","title":"Carolina \"Lina\"","desc":"","updated":1670937078131,"created":1670590878327,"custom":{},"fname":"characters.carolina","type":"note","vault":{"fsPath":".","selfContained":true,"name":"flwiki"},"contentHash":"009a3d5f4c1fb81b0c147d688997d1bb","links":[{"type":"wiki","from":{"fname":"characters.carolina","id":"4iof5rfj4t46eutdqzrax6k","vaultName":"flwiki"},"value":"episodes.season1.leastmagical","alias":"Episode 1","position":{"start":{"line":4,"column":25,"offset":118},"end":{"line":4,"column":68,"offset":161},"indent":[]},"xvault":false,"sameFile":false,"to":{"fname":"episodes.season1.leastmagical"}},{"type":"wiki","from":{"fname":"characters.carolina","id":"4iof5rfj4t46eutdqzrax6k","vaultName":"flwiki"},"value":"Lupe's","alias":"Guadalupe Jara","position":{"start":{"line":4,"column":94,"offset":187},"end":{"line":4,"column":119,"offset":212},"indent":[]},"xvault":false,"sameFile":false,"to":{"fname":"Lupe's"}},{"type":"wiki","from":{"fname":"characters.carolina","id":"4iof5rfj4t46eutdqzrax6k","vaultName":"flwiki"},"value":"episodes.season1.linaandlupe","alias":"Episode 2","position":{"start":{"line":9,"column":4,"offset":922},"end":{"line":9,"column":46,"offset":964},"indent":[]},"xvault":false,"sameFile":false,"to":{"fname":"episodes.season1.linaandlupe"}},{"type":"wiki","from":{"fname":"characters.carolina","id":"4iof5rfj4t46eutdqzrax6k","vaultName":"flwiki"},"value":"episodes.season1.questionslater","alias":"Episode 3","position":{"start":{"line":11,"column":4,"offset":1016},"end":{"line":11,"column":49,"offset":1061},"indent":[]},"xvault":false,"sameFile":false,"to":{"fname":"episodes.season1.questionslater"}},{"type":"wiki","from":{"fname":"characters.carolina","id":"4iof5rfj4t46eutdqzrax6k","vaultName":"flwiki"},"value":"lore.witches","alias":"Witch","position":{"start":{"line":11,"column":140,"offset":1152},"end":{"line":11,"column":162,"offset":1174},"indent":[]},"xvault":false,"sameFile":false,"to":{"fname":"lore.witches"}},{"type":"wiki","from":{"fname":"characters.carolina","id":"4iof5rfj4t46eutdqzrax6k","vaultName":"flwiki"},"value":"episodes.season1.mythofthelady","alias":"Episode 16","position":{"start":{"line":11,"column":627,"offset":1639},"end":{"line":11,"column":672,"offset":1684},"indent":[]},"xvault":false,"sameFile":false,"to":{"fname":"episodes.season1.mythofthelady"}},{"type":"wiki","from":{"fname":"characters.carolina","id":"4iof5rfj4t46eutdqzrax6k","vaultName":"flwiki"},"value":"lore.bells","alias":"Bells","position":{"start":{"line":17,"column":75,"offset":2072},"end":{"line":17,"column":95,"offset":2092},"indent":[]},"xvault":false,"sameFile":false,"to":{"fname":"lore.bells"}},{"type":"wiki","from":{"fname":"characters.carolina","id":"4iof5rfj4t46eutdqzrax6k","vaultName":"flwiki"},"value":"characters.cricket","alias":"The Wolf","position":{"start":{"line":17,"column":155,"offset":2152},"end":{"line":17,"column":186,"offset":2183},"indent":[]},"xvault":false,"sameFile":false,"to":{"fname":"characters.cricket"}},{"from":{"fname":"characters","id":"jx4dpa7wvrmme1hynp7iyon","vaultName":"flwiki"},"type":"backlink","position":{"start":{"line":5,"column":3,"offset":144},"end":{"line":5,"column":26,"offset":167},"indent":[]},"value":"characters.carolina"},{"from":{"fname":"characters.alice","id":"hqherc1dsrtfwq53fxcojvr","vaultName":"flwiki"},"type":"backlink","position":{"start":{"line":9,"column":123,"offset":475},"end":{"line":9,"column":151,"offset":503},"indent":[]},"value":"characters.carolina"},{"from":{"fname":"characters.alvarlambert","id":"lzw2er4a53exd8ojdjlfu7e","vaultName":"flwiki"},"type":"backlink","position":{"start":{"line":5,"column":145,"offset":285},"end":{"line":5,"column":179,"offset":319},"indent":[]},"value":"characters.carolina"},{"from":{"fname":"characters.alvarlambert","id":"lzw2er4a53exd8ojdjlfu7e","vaultName":"flwiki"},"type":"backlink","position":{"start":{"line":24,"column":4,"offset":2343},"end":{"line":24,"column":43,"offset":2382},"indent":[]},"value":"characters.carolina"}],"anchors":{"initial-appearance":{"type":"header","text":"Initial Appearance","value":"initial-appearance","line":9,"column":0,"depth":1},"physical-appearance":{"type":"header","text":"Physical Appearance","value":"physical-appearance","line":12,"column":0,"depth":1},"red-hoods":{"type":"header","text":"Red Hoods","value":"red-hoods","line":19,"column":0,"depth":2},"the-traitor":{"type":"header","text":"The Traitor","value":"the-traitor","line":22,"column":0,"depth":2}},"children":[],"parent":"jx4dpa7wvrmme1hynp7iyon","data":{}}
